mage/__init__.py
mage/query.py
mage/schema.py
mage/api_resources/__init__.py
mage/api_resources/assessment.py
mage/api_resources/assessment_asset_connection.py
mage/api_resources/assessment_asset_group_connection.py
mage/api_resources/assessment_run.py
mage/api_resources/assessment_run_asset_connection.py
mage/api_resources/assessment_run_credential_connection.py
mage/api_resources/asset.py
mage/api_resources/asset_connection.py
mage/api_resources/asset_group.py
mage/api_resources/asset_group_connection.py
mage/api_resources/client.py
mage/api_resources/cloud_credential.py
mage/api_resources/credential.py
mage/api_resources/credential_connection.py
mage/api_resources/finding.py
mage/api_resources/invoice.py
mage/api_resources/lead.py
mage/api_resources/score.py
mage/api_resources/ttp.py
mage/api_resources/abstract/__init__.py
mage/api_resources/abstract/data_api_resource.py
mage/api_resources/abstract/filterable_api_resource.py
mage/api_resources/abstract/listable_api_resource.py
mage/api_resources/abstract/mutable_api_resource.py
mage/api_resources/abstract/util.py
tests/__init__.py
tests/assessment.py
tests/assessment_run.py
tests/asset.py
tests/asset_group.py
tests/invoice.py
tests/lead.py
tests/score.py
tests/ttp.py
tests/mage/__init__.py
tests/mage/query.py
tests/mage/schema.py
tests/mage/api_resources/__init__.py
tests/mage/api_resources/assessment.py
tests/mage/api_resources/assessment_asset_connection.py
tests/mage/api_resources/assessment_asset_group_connection.py
tests/mage/api_resources/assessment_run.py
tests/mage/api_resources/assessment_run_asset_connection.py
tests/mage/api_resources/assessment_run_credential_connection.py
tests/mage/api_resources/asset.py
tests/mage/api_resources/asset_connection.py
tests/mage/api_resources/asset_group.py
tests/mage/api_resources/asset_group_connection.py
tests/mage/api_resources/client.py
tests/mage/api_resources/cloud_credential.py
tests/mage/api_resources/credential.py
magepy-0.2.2.dist-info/LICENSE
magepy-0.2.2.dist-info/METADATA
magepy-0.2.2.dist-info/WHEEL
magepy-0.2.2.dist-info/top_level.txt
magepy-0.2.2.dist-info/RECORD
