Metadata-Version: 2.1
Name: magepy
Version: 0.2.2
Summary: An SDK to interact with MAGE
Home-page: https://github.com/Stage2Sec/magepy
Author: Stage 2 Security
Author-email: magepy@stage2sec.com
License: UNKNOWN
Platform: UNKNOWN
Classifier: Programming Language :: Python :: 3
Classifier: License :: OSI Approved :: MIT License
Classifier: Operating System :: OS Independent
Requires-Python: >=3.5
Requires-Dist: python-dotenv (>=0.15.0)
Requires-Dist: sgqlc (>=11.0)
Requires-Dist: warrant (>=0.6.1)
